{
  "indexes": [
    {
      "collectionGroup": "offers",
      "queryScope": "COLLECTION",
      "fields": [
        { "fieldPath": "status", "order": "ASCENDING" },
        { "fieldPath": "publishDate", "order": "DESCENDING" }
      ]
    },
    {
      "collectionGroup": "offers",
      "queryScope": "COLLECTION",
      "fields": [
        { "fieldPath": "status", "order": "ASCENDING" },
        { "fieldPath": "isVIP", "order": "ASCENDING" },
        { "fieldPath": "publishDate", "order": "DESCENDING" }
      ]
    },
    {
      "collectionGroup": "offers",
      "queryScope": "COLLECTION",
      "fields": [
        { "fieldPath": "status", "order": "ASCENDING" },
        { "fieldPath": "category", "order": "ASCENDING" },
        { "fieldPath": "publishDate", "order": "DESCENDING" }
      ]
    },
    {
      "collectionGroup": "members",
      "queryScope": "COLLECTION",
      "fields": [
        { "fieldPath": "invitedBy", "order": "ASCENDING" },
        { "fieldPath": "createdAt", "order": "DESCENDING" }
      ]
    },
    {
      "collectionGroup": "members",
      "queryScope": "COLLECTION",
      "fields": [
        { "fieldPath": "status", "order": "ASCENDING" },
        { "fieldPath": "createdAt", "order": "DESCENDING" }
      ]
    },
    {
      "collectionGroup": "messages",
      "queryScope": "COLLECTION",
      "fields": [
        { "fieldPath": "senderRole", "order": "ASCENDING" },
        { "fieldPath": "isRead", "order": "ASCENDING" }
      ]
    }
  ],
  "fieldOverrides": []
}
